choicesenum/__init__.py
choicesenum/enums.py
choicesenum/patches.py
choicesenum/django/__init__.py
choicesenum/django/compat.py
choicesenum/django/fields.py
choicesenum/schematics/__init__.py
choicesenum/schematics/types.py
choicesenum-0.7.0.dist-info/AUTHORS.rst
choicesenum-0.7.0.dist-info/LICENSE
choicesenum-0.7.0.dist-info/METADATA
choicesenum-0.7.0.dist-info/WHEEL
choicesenum-0.7.0.dist-info/top_level.txt
choicesenum-0.7.0.dist-info/RECORD
