Metadata-Version: 2.1
Name: choicesenum
Version: 0.7.0
Summary: Python's Enum with extra powers to play nice with labels and choices fields
Home-page: https://github.com/loggi/python-choicesenum
Author: Fernando Macedo
Author-email: fgmacedo@gmail.com
License: BSD license
Keywords: choicesenum
Platform: UNKNOWN
Classifier: Development Status :: 5 - Production/Stable
Classifier: Intended Audience :: Developers
Classifier: License :: OSI Approved :: BSD License
Classifier: Natural Language :: English
Classifier: Programming Language :: Python :: 2
Classifier: Programming Language :: Python :: 2.7
Classifier: Programming Language :: Python :: 3
Classifier: Programming Language :: Python :: 3.5
Classifier: Programming Language :: Python :: 3.6
Classifier: Programming Language :: Python :: 3.7
Classifier: Programming Language :: Python :: 3.8
Requires-Dist: six
Requires-Dist: enum34 ; python_version < "3.4"
